Workbook

Sheet Revenue Model
A1: FitConnect — Unit Economics Model
A2: Luxury Fitness Marketplace | Smart Scheduling
A4: CORE ASSUMPTIONS
A5: Assumption | B5: Month 1 | C5: Month 3 | D5: Month 6 | E5: Month 12 | F5: Month 18 | G5: Month 24
A6: Active Trainers | B6: 50 | C6: 150 | D6: 400 | E6: 1000 | F6: 2000 | G6: 3500
A7: Avg Bookings / Trainer / Month | B7: 4 | C7: 6 | D7: 8 | E7: 10 | F7: 12 | G7: 14
A8: Total Monthly Bookings | B8: =B6*B7 | C8: =C6*C7 | D8: =D6*D7 | E8: =E6*E7 | F8: =F6*F7 | G8: =G6*G7
A9: Avg Session Rate (Trainer-Set) | B9: 40 | C9: 42 | D9: 45 | E9: 48 | F9: 50 | G9: 52
A10: Gross Booking Volume (GMV) | B10: =B8*B9 | C10: =C8*C9 | D10: =D8*D9 | E10: =E8*E9 | F10: =F8*F9 | G10: =G8*G9
A12: PLATFORM FEE SCENARIOS
A13: Fee Structure | B13: Month 1 | C13: Month 3 | D13: Month 6 | E13: Month 12 | F13: Month 18 | G13: Month 24
A14: Fee Rate — Scenario A: 5% | B14: 0.05 | C14: 0.05 | D14: 0.05 | E14: 0.05 | F14: 0.05 | G14: 0.05
A15: Revenue — Scenario A: 5% | B15: =B10*B14 | C15: =C10*C14 | D15: =D10*D14 | E15: =E10*E14 | F15: =F10*F14 | G15: =G10*G14
A16: Fee Rate — Scenario B: 8% | B16: 0.08 | C16: 0.08 | D16: 0.08 | E16: 0.08 | F16: 0.08 | G16: 0.08
A17: Revenue — Scenario B: 8% | B17: =B10*B16 | C17: =C10*C16 | D17: =D10*D16 | E17: =E10*E16 | F17: =F10*F16 | G17: =G10*G16
A18: Fee Rate — Scenario C: 10% | B18: 0.1 | C18: 0.1 | D18: 0.1 | E18: 0.1 | F18: 0.1 | G18: 0.1
A19: Revenue — Scenario C: 10% | B19: =B10*B18 | C19: =C10*C18 | D19: =D10*D18 | E19: =E10*E18 | F19: =F10*F18 | G19: =G10*G18
A20: Fee Rate — Scenario D: 12% | B20: 0.12 | C20: 0.12 | D20: 0.12 | E20: 0.12 | F20: 0.12 | G20: 0.12
A21: Revenue — Scenario D: 12% | B21: =B10*B20 | C21: =C10*C20 | D21: =D10*D20 | E21: =E10*E20 | F21: =F10*F20 | G21: =G10*G20
A23: TRAINER SUBSCRIPTION ($5/mo)
A24: Item | B24: Month 1 | C24: Month 3 | D24: Month 6 | E24: Month 12 | F24: Month 18 | G24: Month 24
A25: Subscription Price | B25: 5 | C25: 5 | D25: 5 | E25: 5 | F25: 5 | G25: 5
A26: Adoption Rate | B26: 0.05 | C26: 0.1 | D26: 0.15 | E26: 0.2 | F26: 0.25 | G26: 0.3
A27: Subscribing Trainers | B27: =ROUND(B6*B26,0) | C27: =ROUND(C6*C26,0) | D27: =ROUND(D6*D26,0) | E27: =ROUND(E6*E26,0) | F27: =ROUND(F6*F26,0) | G27: =ROUND(G6*G26,0)
A28: Subscription Revenue | B28: =B27*B25 | C28: =C27*C25 | D28: =D27*D25 | E28: =E27*E25 | F28: =F27*F25 | G28: =G27*G25
A30: TOTAL REVENUE (8% fee)
A31: Source | B31: Month 1 | C31: Month 3 | D31: Month 6 | E31: Month 12 | F31: Month 18 | G31: Month 24
A32: Platform Fee Revenue (8%) | B32: =B17 | C32: =C17 | D32: =D17 | E32: =E17 | F32: =F17 | G32: =G17
A33: Subscription Revenue | B33: =B28 | C33: =C28 | D33: =D28 | E33: =E28 | F33: =F28 | G33: =G28
A34: TOTAL GROSS REVENUE | B34: =B32+B33 | C34: =C32+C33 | D34: =D32+D33 | E34: =E32+E33 | F34: =F32+F33 | G34: =G32+G33

Sheet Payment Processing
A1: Payment Method Cost Comparison
A3: PER-TRANSACTION COSTS
A4: Payment Method | B4: Rate (%) | C4: Fixed Fee | D4: Cost on $40 | E4: Cost on $55
A5: Credit Card (Stripe) | B5: 0.029 | C5: 0.3 | D5: =40*B5+C5 | E5: =55*B5+C5
A6: Debit Card (Stripe) | B6: 0.005 | C6: 0.21 | D6: =40*B6+C6 | E6: =55*B6+C6
A7: Venmo (Business) | B7: 0.019 | C7: 0.1 | D7: =40*B7+C7 | E7: =55*B7+C7
A8: Zelle | B8: 0 | C8: 0 | D8: =40*B8+C8 | E8: =55*B8+C8
A9: Apple Pay (via Stripe) | B9: 0.029 | C9: 0.3 | D9: =40*B9+C9 | E9: =55*B9+C9
A10: ACH Bank Transfer | B10: 0.008 | C10: 0 | D10: =40*B10+C10 | E10: =55*B10+C10
A12: NET REVENUE PER BOOKING (8% fee on $40)
A13: Payment Method | B13: Platform Fee | C13: Processing Cost | D13: Net Revenue | E13: Net Margin
A14: =A5 | B14: =40*0.08 | C14: =D5 | D14: =B14-C14 | E14: =IF(B14=0,0,D14/B14)
A15: =A6 | B15: =40*0.08 | C15: =D6 | D15: =B15-C15 | E15: =IF(B15=0,0,D15/B15)
A16: =A7 | B16: =40*0.08 | C16: =D7 | D16: =B16-C16 | E16: =IF(B16=0,0,D16/B16)
A17: =A8 | B17: =40*0.08 | C17: =D8 | D17: =B17-C17 | E17: =IF(B17=0,0,D17/B17)
A18: =A9 | B18: =40*0.08 | C18: =D9 | D18: =B18-C18 | E18: =IF(B18=0,0,D18/B18)
A19: =A10 | B19: =40*0.08 | C19: =D10 | D19: =B19-C19 | E19: =IF(B19=0,0,D19/B19)
A21: PAYMENT MIX SCENARIOS
A22: Payment Method | B22: Default Mix | C22: Wtd Cost | D22: Incentivized Mix | E22: Wtd Cost
A23: =A5 | B23: 0.5 | C23: =B23*D5 | D23: 0.25 | E23: =D23*D5
A24: =A6 | B24: 0.15 | C24: =B24*D6 | D24: 0.25 | E24: =D24*D6
A25: =A7 | B25: 0.15 | C25: =B25*D7 | D25: 0.2 | E25: =D25*D7
A26: =A8 | B26: 0.1 | C26: =B26*D8 | D26: 0.2 | E26: =D26*D8
A27: =A9 | B27: 0.05 | C27: =B27*D9 | D27: 0.05 | E27: =D27*D9
A28: =A10 | B28: 0.05 | C28: =B28*D10 | D28: 0.05 | E28: =D28*D10
A29: BLENDED COST / TRANSACTION | C29: =SUM(C23:C28) | E29: =SUM(E23:E28)
A30: SAVINGS PER TXN FROM INCENTIVIZED MIX | E30: =C29-E29

Sheet Operating Costs
A1: Monthly Operating Costs
A3: MONTHLY COSTS
A4: Cost Category | B4: Month 1 | C4: Month 3 | D4: Month 6 | E4: Month 12 | F4: Month 18 | G4: Month 24
A5: Cloud Infrastructure | B5: 500 | C5: 800 | D5: 1500 | E5: 3000 | F5: 5000 | G5: 8000
A6: ID Verification Service | B6: 200 | C6: 400 | D6: 600 | E6: 800 | F6: 1000 | G6: 1200
A7: SMS / Email Services | B7: 100 | C7: 300 | D7: 600 | E7: 1200 | F7: 2000 | G7: 3000
A8: Calendar API | B8: 50 | C8: 100 | D8: 200 | E8: 400 | F8: 600 | G8: 800
A9: Customer Support | B9: 0 | C9: 1000 | D9: 2500 | E9: 5000 | F9: 8000 | G9: 12000
A10: Insurance / Legal | B10: 500 | C10: 500 | D10: 750 | E10: 1000 | F10: 1500 | G10: 2000
A11: Marketing / CAC | B11: 2000 | C11: 5000 | D11: 10000 | E11: 20000 | F11: 35000 | G11: 50000
A12: Misc / Contingency | B12: 500 | C12: 500 | D12: 1000 | E12: 1500 | F12: 2000 | G12: 3000
A13: Subtotal Fixed Costs | B13: =SUM(B5:B12) | C13: =SUM(C5:C12) | D13: =SUM(D5:D12) | E13: =SUM(E5:E12) | F13: =SUM(F5:F12) | G13: =SUM(G5:G12)
A15: PER-TRAINER ONBOARDING COSTS
A16: Item | B16: Month 1 | C16: Month 3 | D16: Month 6 | E16: Month 12 | F16: Month 18 | G16: Month 24
A17: New Trainers This Period | B17: 50 | C17: 100 | D17: 250 | E17: 600 | F17: 1000 | G17: 1500
A18: Background Check ($/trainer) | B18: 35 | C18: 35 | D18: 35 | E18: 35 | F18: 35 | G18: 35
A19: Photography ($/trainer) | B19: 100 | C19: 100 | D19: 100 | E19: 100 | F19: 100 | G19: 100
A20: Total Onboarding Costs | B20: =B17*(B18+B19) | C20: =C17*(C18+C19) | D20: =D17*(D18+D19) | E20: =E17*(E18+E19) | F20: =F17*(F18+F19) | G20: =G17*(G18+G19)
A22: TOTAL MONTHLY COSTS | B22: =B13+B20 | C22: =C13+C20 | D22: =D13+D20 | E22: =E13+E20 | F22: =F13+F20 | G22: =G13+G20

Sheet P&L Summary
A1: Profit & Loss Summary (8% Fee Scenario)
A3: REVENUE
A4: Line Item | B4: Month 1 | C4: Month 3 | D4: Month 6 | E4: Month 12 | F4: Month 18 | G4: Month 24
A5: GMV | B5: ='Revenue Model'!B10 | C5: ='Revenue Model'!C10 | D5: ='Revenue Model'!D10 | E5: ='Revenue Model'!E10 | F5: ='Revenue Model'!F10 | G5: ='Revenue Model'!G10
A6: Platform Fee Revenue (8%) | B6: ='Revenue Model'!B17 | C6: ='Revenue Model'!C17 | D6: ='Revenue Model'!D17 | E6: ='Revenue Model'!E17 | F6: ='Revenue Model'!F17 | G6: ='Revenue Model'!G17
A7: Subscription Revenue | B7: ='Revenue Model'!B28 | C7: ='Revenue Model'!C28 | D7: ='Revenue Model'!D28 | E7: ='Revenue Model'!E28 | F7: ='Revenue Model'!F28 | G7: ='Revenue Model'!G28
A8: TOTAL REVENUE | B8: =B6+B7 | C8: =C6+C7 | D8: =D6+D7 | E8: =E6+E7 | F8: =F6+F7 | G8: =G6+G7
A10: COSTS
A11: Payment Processing (blended) | B11: ='Revenue Model'!B8*'Payment Processing'!C29 | C11: ='Revenue Model'!C8*'Payment Processing'!C29 | D11: ='Revenue Model'!D8*'Payment Processing'!C29 | E11: ='Revenue Model'!E8*'Payment Processing'!C29 | F11: ='Revenue Model'!F8*'Payment Processing'!C29 | G11: ='Revenue Model'!G8*'Payment Processing'!C29
A12: Operating Costs | B12: ='Operating Costs'!B22 | C12: ='Operating Costs'!C22 | D12: ='Operating Costs'!D22 | E12: ='Operating Costs'!E22 | F12: ='Operating Costs'!F22 | G12: ='Operating Costs'!G22
A13: TOTAL COSTS | B13: =B11+B12 | C13: =C11+C12 | D13: =D11+D12 | E13: =E11+E12 | F13: =F11+F12 | G13: =G11+G12
A15: NET PROFIT / (LOSS) | B15: =B8-B13 | C15: =C8-C13 | D15: =D8-D13 | E15: =E8-E13 | F15: =F8-F13 | G15: =G8-G13
A16: Net Margin | B16: =IF(B8=0,0,B15/B8) | C16: =IF(C8=0,0,C15/C8) | D16: =IF(D8=0,0,D15/D8) | E16: =IF(E8=0,0,E15/E8) | F16: =IF(F8=0,0,F15/F8) | G16: =IF(G8=0,0,G15/G8)
A18: KEY METRICS
A19: Metric | B19: Month 1 | C19: Month 3 | D19: Month 6 | E19: Month 12 | F19: Month 18 | G19: Month 24
A20: Revenue per Trainer / Month | B20: =IF('Revenue Model'!B6=0,0,B8/'Revenue Model'!B6) | C20: =IF('Revenue Model'!C6=0,0,C8/'Revenue Model'!C6) | D20: =IF('Revenue Model'!D6=0,0,D8/'Revenue Model'!D6) | E20: =IF('Revenue Model'!E6=0,0,E8/'Revenue Model'!E6) | F20: =IF('Revenue Model'!F6=0,0,F8/'Revenue Model'!F6) | G20: =IF('Revenue Model'!G6=0,0,G8/'Revenue Model'!G6)
A21: Revenue per Booking | B21: =IF('Revenue Model'!B8=0,0,B8/'Revenue Model'!B8) | C21: =IF('Revenue Model'!C8=0,0,C8/'Revenue Model'!C8) | D21: =IF('Revenue Model'!D8=0,0,D8/'Revenue Model'!D8) | E21: =IF('Revenue Model'!E8=0,0,E8/'Revenue Model'!E8) | F21: =IF('Revenue Model'!F8=0,0,F8/'Revenue Model'!F8) | G21: =IF('Revenue Model'!G8=0,0,G8/'Revenue Model'!G8)
A22: Cost per Booking | B22: =IF('Revenue Model'!B8=0,0,B13/'Revenue Model'!B8) | C22: =IF('Revenue Model'!C8=0,0,C13/'Revenue Model'!C8) | D22: =IF('Revenue Model'!D8=0,0,D13/'Revenue Model'!D8) | E22: =IF('Revenue Model'!E8=0,0,E13/'Revenue Model'!E8) | F22: =IF('Revenue Model'!F8=0,0,F13/'Revenue Model'!F8) | G22: =IF('Revenue Model'!G8=0,0,G13/'Revenue Model'!G8)
A23: Effective Take Rate (incl. subs) | B23: =IF(B5=0,0,B8/B5) | C23: =IF(C5=0,0,C8/C5) | D23: =IF(D5=0,0,D8/D5) | E23: =IF(E5=0,0,E8/E5) | F23: =IF(F5=0,0,F8/F5) | G23: =IF(G5=0,0,G8/G5)

Sheet Assumptions
A1: Key Assumptions & Notes
A3: Geography | B3: US launch, single city first (hyper-local)
A4: Session Rate | B4: Trainer-set "optimized rate" — never called a discount
A5: Platform Fee | B5: 8% recommended. Below gyms (30-60%) and ClassPass (20-30%)
A6: Subscription | B6: $5/mo for analytics, slot boost, featured, instant payouts
A7: Processing | B7: Costs passed to payer. Incentivize debit/Zelle/Venmo
A8: Background Check | B8: $25-50/trainer, one-time at onboarding
A9: Photography | B9: Professional or AI-enhanced. ~$100/trainer
A10: Trainer Churn | B10: 80% industry first-year quit rate. Model shows net growth
A11: Bookings/Trainer | B11: Conservative 4/mo start, 14/mo at scale
A12: Cold Start | B12: Months 1-3 require heavy marketing to seed supply
A13: AI Phase 1 | B13: Calendar sync + idle detection. No ML needed
A14: AI Phase 2+ | B14: Pattern analysis, demand heatmaps, smart pricing
... A18: Payments | B18: Stripe Connect + Zelle + Venmo for lower costs
